{
  "id": "day.afternoon.none.high-surf",
  "apiVersion": "1.0.0",
  "rendererVersion": "global-library-2026-07",
  "label": "Afternoon · High surf",
  "mode": "day",
  "phase": "afternoon",
  "moonPhase": null,
  "weather": "high-surf",
  "family": "tropical-marine",
  "category": "tropical-marine",
  "effect": "high-surf",
  "windProfile": "open-air",
  "attributes": {
    "key": "high-surf",
    "en": "High surf",
    "family": "tropical-marine",
    "category": "tropical-marine",
    "effect": "high-surf",
    "marine": 3,
    "cloud": 1,
    "wind": 3
  },
  "links": {
    "self": "https://afnan-hossain.github.io/atmoscene/api/v1/scenes/by-id/day.afternoon.none.high-surf.json",
    "collection": "https://afnan-hossain.github.io/atmoscene/api/v1/collections/tropical-marine.json",
    "preview": "https://afnan-hossain.github.io/atmoscene/api/demo/?scene=day.afternoon.none.high-surf"
  },
  "runtime": {
    "mode": "day",
    "phase": "afternoon",
    "moonPhase": null,
    "weather": "high-surf",
    "seed": 2120
  }
}
